drawio2png_mcp/__init__.py
drawio2png_mcp-0.1.0.dist-info/METADATA
drawio2png_mcp-0.1.0.dist-info/WHEEL
drawio2png_mcp-0.1.0.dist-info/entry_points.txt
drawio2png_mcp-0.1.0.dist-info/RECORD
