Metadata-Version: 2.4
Name: drawio2png-mcp
Version: 0.1.0
Summary: MCP Server for converting Draw.io diagrams to PNG
Project-URL: Homepage, https://github.com/co-pine/drawio2png-mcp
Project-URL: Repository, https://github.com/co-pine/drawio2png-mcp
Author: pine
License: MIT
Keywords: converter,diagram,drawio,mcp,png
Classifier: Development Status :: 4 - Beta
Classifier: Intended Audience :: Developers
Classifier: License :: OSI Approved :: MIT License
Classifier: Programming Language :: Python :: 3
Classifier: Programming Language :: Python :: 3.10
Classifier: Programming Language :: Python :: 3.11
Classifier: Programming Language :: Python :: 3.12
Requires-Python: >=3.10
Requires-Dist: mcp[cli]>=1.0.0
